<?xml version="1.0" encoding="UTF-8"?>
<!DOCTYPE mapper PUBLIC "-//mybatis.org//DTD Mapper 3.0//EN" "http://mybatis.org/dtd/mybatis-3-mapper.dtd">
<mapper namespace="com.vrv.cems.dao.CemsUserMapper">
  <resultMap id="BaseResultMap" type="com.vrv.cems.pojo.CemsUser">
    <!--
      WARNING - @mbggenerated
      This element is automatically generated by MyBatis Generator, do not modify.
    -->
    <id column="id" jdbcType="VARCHAR" property="id" />
    <result column="userName" jdbcType="VARCHAR" property="username" />
    <result column="phone" jdbcType="VARCHAR" property="phone" />
    <result column="createTime" jdbcType="TIMESTAMP" property="createtime" />
    <result column="updateTime" jdbcType="TIMESTAMP" property="updatetime" />
  </resultMap>
  <sql id="Base_Column_List">
    <!--
      WARNING - @mbggenerated
      This element is automatically generated by MyBatis Generator, do not modify.
    -->
    id, userName, phone, createTime, updateTime
  </sql>
  <select id="selectByPrimaryKey" parameterType="java.lang.String" resultMap="BaseResultMap">
    <!--
      WARNING - @mbggenerated
      This element is automatically generated by MyBatis Generator, do not modify.
    -->
    select 
    <include refid="Base_Column_List" />
    from cems_user
    where id = #{id,jdbcType=VARCHAR}
  </select>
  <delete id="deleteByPrimaryKey" parameterType="java.lang.String">
    <!--
      WARNING - @mbggenerated
      This element is automatically generated by MyBatis Generator, do not modify.
    -->
    delete from cems_user
    where id = #{id,jdbcType=VARCHAR}
  </delete>
  <insert id="insert" parameterType="com.vrv.cems.pojo.CemsUser">
    <!--
      WARNING - @mbggenerated
      This element is automatically generated by MyBatis Generator, do not modify.
    -->
    insert into cems_user (id, userName, phone, 
      createTime, updateTime)
    values (#{id,jdbcType=VARCHAR}, #{username,jdbcType=VARCHAR}, #{phone,jdbcType=VARCHAR}, 
      #{createtime,jdbcType=TIMESTAMP}, #{updatetime,jdbcType=TIMESTAMP})
  </insert>
  <insert id="insertSelective" parameterType="com.vrv.cems.pojo.CemsUser">
    <!--
      WARNING - @mbggenerated
      This element is automatically generated by MyBatis Generator, do not modify.
    -->
    insert into cems_user
    <trim prefix="(" suffix=")" suffixOverrides=",">
      <if test="id != null">
        id,
      </if>
      <if test="username != null">
        userName,
      </if>
      <if test="phone != null">
        phone,
      </if>
      <if test="createtime != null">
        createTime,
      </if>
      <if test="updatetime != null">
        updateTime,
      </if>
    </trim>
    <trim prefix="values (" suffix=")" suffixOverrides=",">
      <if test="id != null">
        #{id,jdbcType=VARCHAR},
      </if>
      <if test="username != null">
        #{username,jdbcType=VARCHAR},
      </if>
      <if test="phone != null">
        #{phone,jdbcType=VARCHAR},
      </if>
      <if test="createtime != null">
        #{createtime,jdbcType=TIMESTAMP},
      </if>
      <if test="updatetime != null">
        #{updatetime,jdbcType=TIMESTAMP},
      </if>
    </trim>
  </insert>
  <update id="updateByPrimaryKeySelective" parameterType="com.vrv.cems.pojo.CemsUser">
    <!--
      WARNING - @mbggenerated
      This element is automatically generated by MyBatis Generator, do not modify.
    -->
    update cems_user
    <set>
      <if test="username != null">
        userName = #{username,jdbcType=VARCHAR},
      </if>
      <if test="phone != null">
        phone = #{phone,jdbcType=VARCHAR},
      </if>
      <if test="createtime != null">
        createTime = #{createtime,jdbcType=TIMESTAMP},
      </if>
      <if test="updatetime != null">
        updateTime = #{updatetime,jdbcType=TIMESTAMP},
      </if>
    </set>
    where id = #{id,jdbcType=VARCHAR}
  </update>
  <update id="updateByPrimaryKey" parameterType="com.vrv.cems.pojo.CemsUser">
    <!--
      WARNING - @mbggenerated
      This element is automatically generated by MyBatis Generator, do not modify.
    -->
    update cems_user
    set userName = #{username,jdbcType=VARCHAR},
      phone = #{phone,jdbcType=VARCHAR},
      createTime = #{createtime,jdbcType=TIMESTAMP},
      updateTime = #{updatetime,jdbcType=TIMESTAMP}
    where id = #{id,jdbcType=VARCHAR}
  </update>

  <!--我自己加的方法-->
  <select id="findAllUser" resultType="com.vrv.cems.pojo.CemsUser">
    select * from cems_user
  </select>

</mapper>